MANIFEST.in
README.md
setup.py
pysg/__init__.py
pysg/camera.py
pysg/geometry.py
pysg/light.py
pysg/node_3d.py
pysg/object_3d.py
pysg/pyrr_extensions.py
pysg/renderer.py
pysg/scene.py
pysg/testing.py
pysg/util.py
pysg/version.py
pysg.egg-info/PKG-INFO
pysg.egg-info/SOURCES.txt
pysg.egg-info/dependency_links.txt
pysg.egg-info/not-zip-safe
pysg.egg-info/requires.txt
pysg.egg-info/top_level.txt
pysg/constants/__init__.py
pysg/constants/color.py
pysg/error/__init__.py
pysg/shader/simple.frag
pysg/shader/simple.vert
tests/__init__.py
tests/test_camera.py
tests/test_node3D.py
tests/test_pyrr_extensions.py
tests/test_scene.py
tests/test_util.py