Metadata-Version: 2.1
Name: pysg
Version: 0.1.5
Summary: Simple and lightweight 3D render scene graph for python
Home-page: https://gitlab.com/becheran/pysg
Author: Armin Becher
Author-email: becherarmin@gmail.com
License: MIT
Platform: UNKNOWN
Classifier: Programming Language :: Python :: 3
Classifier: License :: OSI Approved :: MIT License
Classifier: Operating System :: OS Independent
Requires-Python: >=3.6
